{
  "contacts": [
    {
      "id": "Dhshgjhjsh",
      "nome": "Marcos",
      "company": "dkp----",
      "email": "Marcos@gmail.com.br",
      "titulo": "programador123",
      "telefone": "9876546787",
      "photo": "https://cdn-icons-png.flaticon.com/128/219/219988.png",
      "grupoId": "1"
    },
    {
      "id": "Njsohg",
      "nome": "Maria Elena",
      "company": "Mercado",
      "email": "Marcos@gmail.com",
      "titulo": "gerente",
      "telefone": "9876546787",
      "photo": "https://cdn-icons-png.flaticon.com/512/219/219987.png",
      "grupoId": "2"
    }
  ],
  "groups": [
    {
      "id": "1",
      "nome": "Colleague"
    },
    {
      "id": "2",
      "nome": "Friend"
    },
    {
      "id": "3",
      "nome": "Family"
    }
  ]
}